latexgen/__init__.py
latexgen/__version__.py
latexgen/latex.py
latexgen_hw_itmo-1.0.3.dist-info/licenses/LICENSE
latexgen_hw_itmo-1.0.3.dist-info/METADATA
latexgen_hw_itmo-1.0.3.dist-info/WHEEL
latexgen_hw_itmo-1.0.3.dist-info/top_level.txt
latexgen_hw_itmo-1.0.3.dist-info/RECORD
