Metadata-Version: 2.4
Name: latexgen-hw-itmo
Version: 1.0.3
Summary: LaTeX table and image generator
Home-page: https://github.com/ваш-username/latexgen
Author: sudokushifter
Author-email: Mihail Borodin <zanid227@yandex.ru>
Project-URL: Homepage, https://github.com/sudokushifter/latexgen
Project-URL: Bug Tracker, https://github.com/sudokushifter/latexgen/issues
Classifier: Programming Language :: Python :: 3
Classifier: License :: OSI Approved :: MIT License
Classifier: Operating System :: OS Independent
Classifier: Topic :: Text Processing :: Markup :: LaTeX
Requires-Python: >=3.7
License-File: LICENSE
Dynamic: author
Dynamic: home-page
Dynamic: license-file
Dynamic: requires-python
